README.txt
setup.py
LexTengLib/__init__.py
LexTengLib/xfile.py
LexTengLib/xlogger.py
LexTengLib/xtensorflow.py
LexTengLib/xtime.py
LexTengLib.egg-info/PKG-INFO
LexTengLib.egg-info/SOURCES.txt
LexTengLib.egg-info/dependency_links.txt
LexTengLib.egg-info/top_level.txt
LexTengLib.egg-info/zip-safe