Metadata-Version: 1.1
Name: LexTengLib
Version: 0.5.0
Summary: This is a private library of Lex.Teng. Free for anyone to use.
Home-page: http://lexteng.cn
Author: LexTeng
Author-email: lexteng@163.com
License: MIT
Keywords: private library
Platform: UNKNOWN
Classifier: License :: OSI Approved :: MIT License
Classifier: Programming Language :: Python
Classifier: Intended Audience :: Developers
Classifier: Operating System :: OS Independent
